[
  {
    "id": 1781727792731,
    "payload": {
      "type": "contact_message",
      "messageId": 1781727792726,
      "createdAt": "2026-06-17T20:23:12.725Z"
    },
    "attempts": 0,
    "nextAttemptAt": 1781727792731
  },
  {
    "id": 1781727792737,
    "payload": {
      "type": "contact_message",
      "messageId": 1781727792732,
      "createdAt": "2026-06-17T20:23:12.732Z"
    },
    "attempts": 0,
    "nextAttemptAt": 1781727792737
  },
  {
    "id": 1781727792742,
    "payload": {
      "type": "contact_message",
      "messageId": 1781727792738,
      "createdAt": "2026-06-17T20:23:12.737Z"
    },
    "attempts": 0,
    "nextAttemptAt": 1781727792742
  },
  {
    "id": 1781727792749,
    "payload": {
      "type": "contact_message",
      "messageId": 1781727792743,
      "createdAt": "2026-06-17T20:23:12.743Z"
    },
    "attempts": 0,
    "nextAttemptAt": 1781727792749
  }
]